dremioframe/__init__.py
dremioframe/admin.py
dremioframe/async_client.py
dremioframe/batch.py
dremioframe/builder.py
dremioframe/catalog.py
dremioframe/cli.py
dremioframe/client.py
dremioframe/connection_pool.py
dremioframe/cost_estimator.py
dremioframe/flight_sql.py
dremioframe/functions.py
dremioframe/iceberg.py
dremioframe/incremental.py
dremioframe/lineage.py
dremioframe/linter.py
dremioframe/local_builder.py
dremioframe/middleware.py
dremioframe/notebook.py
dremioframe/profile.py
dremioframe/quality.py
dremioframe/schema_evolution.py
dremioframe/templates.py
dremioframe/udf.py
dremioframe/utils.py
dremioframe/ai/__init__.py
dremioframe/ai/agent.py
dremioframe/ai/server.py
dremioframe/airflow/__init__.py
dremioframe/airflow/hooks.py
dremioframe/airflow/operators.py
dremioframe/dq/__init__.py
dremioframe/dq/runner.py
dremioframe/ingest/__init__.py
dremioframe/ingest/database.py
dremioframe/ingest/dlt.py
dremioframe/ingest/files.py
dremioframe/orchestration/__init__.py
dremioframe/orchestration/backend.py
dremioframe/orchestration/decorators.py
dremioframe/orchestration/dremio_tasks.py
dremioframe/orchestration/executors.py
dremioframe/orchestration/iceberg_tasks.py
dremioframe/orchestration/pipeline.py
dremioframe/orchestration/quality.py
dremioframe/orchestration/reflection_tasks.py
dremioframe/orchestration/scheduling.py
dremioframe/orchestration/sensors.py
dremioframe/orchestration/task.py
dremioframe/orchestration/ui.py
dremioframe/orchestration/tasks/builder_task.py
dremioframe/orchestration/tasks/dbt_task.py
dremioframe/orchestration/tasks/dq_task.py
dremioframe/orchestration/tasks/general.py
dremioframe/testing/__init__.py
dremioframe/testing/assertions.py
dremioframe/testing/fixtures.py
dremioframe/testing/mock_client.py
dremioframe-0.25.1.dist-info/entry_points.txt
dremioframe-0.25.1.dist-info/licenses/LICENSE
dremioframe-0.25.1.dist-info/WHEEL
dremioframe-0.25.1.dist-info/METADATA
dremioframe-0.25.1.dist-info/RECORD
