Metadata-Version: 2.4
Name: dremioframe
Version: 0.25.1
Summary: A dataframe-like library for Dremio Cloud & Dremio Software
Author-email: Alex Merced <alexmerced@alexmerced.com>
Requires-Python: >=3.9
Classifier: Programming Language :: Python :: 3
Classifier: License :: OSI Approved :: MIT License
Classifier: Operating System :: OS Independent
License-File: LICENSE
Requires-Dist: pyarrow>=14.0.0
Requires-Dist: pandas>=2.0.0
Requires-Dist: requests>=2.31.0
Requires-Dist: python-dotenv>=1.0.0
Requires-Dist: polars>=0.20.0
Requires-Dist: matplotlib
Requires-Dist: typer>=0.9.0
Requires-Dist: pydantic>=2.0.0
Requires-Dist: aiohttp>=3.8.0
Requires-Dist: datafusion>=33.0.0
Requires-Dist: plotly>=5.0.0
Requires-Dist: pyiceberg>=0.5.0
Requires-Dist: pyyaml>=6.0
Requires-Dist: langchain ; extra == "ai"
Requires-Dist: langchain-openai ; extra == "ai"
Requires-Dist: langchain-anthropic ; extra == "ai"
Requires-Dist: langchain-google-genai ; extra == "ai"
Requires-Dist: langgraph-checkpoint-sqlite ; extra == "ai"
Requires-Dist: apache-airflow ; extra == "airflow"
Requires-Dist: fastavro ; extra == "avro"
Requires-Dist: celery ; extra == "celery"
Requires-Dist: redis ; extra == "celery"
Requires-Dist: rich ; extra == "cli"
Requires-Dist: prompt_toolkit ; extra == "cli"
Requires-Dist: connectorx ; extra == "database"
Requires-Dist: sqlalchemy ; extra == "database"
Requires-Dist: deltalake ; extra == "delta"
Requires-Dist: pytest>=7.0.0 ; extra == "dev"
Requires-Dist: pytest-asyncio ; extra == "dev"
Requires-Dist: requests-mock ; extra == "dev"
Requires-Dist: mkdocs ; extra == "docs"
Requires-Dist: mkdocs-material ; extra == "docs"
Requires-Dist: mkdocstrings[python] ; extra == "docs"
Requires-Dist: pdfplumber ; extra == "document"
Requires-Dist: pyyaml ; extra == "dq"
Requires-Dist: openpyxl ; extra == "excel"
Requires-Dist: lxml ; extra == "html"
Requires-Dist: html5lib ; extra == "html"
Requires-Dist: beautifulsoup4 ; extra == "html"
Requires-Dist: kaleido ; extra == "image-export"
Requires-Dist: dlt ; extra == "ingest"
Requires-Dist: pylance ; extra == "lance"
Requires-Dist: networkx ; extra == "lineage"
Requires-Dist: graphviz ; extra == "lineage"
Requires-Dist: langchain-mcp-adapters ; extra == "mcp"
Requires-Dist: mysql-connector-python ; extra == "mysql"
Requires-Dist: tqdm ; extra == "notebook"
Requires-Dist: ipywidgets ; extra == "notebook"
Requires-Dist: psycopg2-binary ; extra == "postgres"
Requires-Dist: boto3 ; extra == "s3"
Requires-Dist: apscheduler ; extra == "scheduler"
Requires-Dist: mcp ; extra == "server"
Project-URL: Homepage, https://github.com/developer-advocacy-dremio/dremio-cloud-dremioframe
Project-URL: Issues, https://github.com/developer-advocacy-dremio/dremio-cloud-dremioframe/issues
Provides-Extra: ai
Provides-Extra: airflow
Provides-Extra: avro
Provides-Extra: celery
Provides-Extra: cli
Provides-Extra: database
Provides-Extra: delta
Provides-Extra: dev
Provides-Extra: docs
Provides-Extra: document
Provides-Extra: dq
Provides-Extra: excel
Provides-Extra: html
Provides-Extra: image-export
Provides-Extra: ingest
Provides-Extra: lance
Provides-Extra: lineage
Provides-Extra: mcp
Provides-Extra: mysql
Provides-Extra: notebook
Provides-Extra: postgres
Provides-Extra: s3
Provides-Extra: scheduler
Provides-Extra: server
